alimata/__init__.py
alimata/actuators/__init__.py
alimata/actuators/actuator.py
alimata/actuators/lcd.py
alimata/actuators/lcd4bit.py
alimata/actuators/led.py
alimata/actuators/ledRGB.py
alimata/actuators/matrix.py
alimata/actuators/piezo.py
alimata/actuators/servo.py
alimata/actuators/stepper.py
alimata/core/__init__.py
alimata/core/board.py
alimata/core/core.py
alimata/core/error.py
alimata/sensors/__init__.py
alimata/sensors/button.py
alimata/sensors/dht.py
alimata/sensors/knock.py
alimata/sensors/luminosity.py
alimata/sensors/moisture.py
alimata/sensors/motion.py
alimata/sensors/potentiometer.py
alimata/sensors/sensor.py
alimata/sensors/sonar.py
alimata-1.0.1.dist-info/METADATA
alimata-1.0.1.dist-info/WHEEL
alimata-1.0.1.dist-info/top_level.txt
alimata-1.0.1.dist-info/RECORD
