Metadata-Version: 2.1
Name: alimata
Version: 1.0.1
Summary: Alimata is a Python library to simplify the use of the pymata-express library.
Home-page: https://github.com/ALIVEcode/alimata
Author: Nils Lahaye and Francis M-G researchers at LRIMa
Author-email: alivecode.developers@gmail.com
Classifier: Programming Language :: Python :: 3
Classifier: Programming Language :: Python :: 3.7
Requires-Python: >=3.7
Requires-Dist: firmetix >=7.1.1
